moncef_colors/__init__.py
moncef_color_utils_demo-0.0.8.dist-info/METADATA
moncef_color_utils_demo-0.0.8.dist-info/WHEEL
moncef_color_utils_demo-0.0.8.dist-info/licenses/LICENSE
moncef_color_utils_demo-0.0.8.dist-info/RECORD
