Metadata-Version: 2.4
Name: moncef-color-utils-demo
Version: 0.0.8
Summary: A simple utility package for handling colors by Moncef
Author: Moncef
License-File: LICENSE
Classifier: License :: OSI Approved :: MIT License
Classifier: Operating System :: OS Independent
Classifier: Programming Language :: Python :: 3
Requires-Python: >=3.7
